skdoc/__init__.py
skdoc/placeholder.py
skdoc/report.py
skdoc-0.0.1.5.dist-info/LICENSE
skdoc-0.0.1.5.dist-info/METADATA
skdoc-0.0.1.5.dist-info/WHEEL
skdoc-0.0.1.5.dist-info/top_level.txt
skdoc-0.0.1.5.dist-info/RECORD
