Metadata-Version: 2.1
Name: skdoc
Version: 0.0.1.5
Summary: Automated documentation engine for scikit-learn models
Home-page: UNKNOWN
Author: Denis Abdullin, Emile Antat
Author-email: denisabdullincz@gmail.com, eoea754@gmail.com
License: UNKNOWN
Keywords: python,scikit-learn,sklearn,machine learning,documentation
Platform: UNKNOWN
Classifier: Development Status :: 1 - Planning
Classifier: Intended Audience :: Developers
Classifier: Programming Language :: Python :: 3
Classifier: Operating System :: Unix
Classifier: Operating System :: MacOS :: MacOS X
Classifier: Operating System :: Microsoft :: Windows
License-File: LICENSE
Requires-Dist: pandas (>=1.0.0)
Requires-Dist: scikit-learn (>=1.0.0)
Requires-Dist: quarto
Requires-Dist: subprocess
Requires-Dist: pyecharts
Requires-Dist: webbrowser
Provides-Extra: dev
Requires-Dist: pytest (>=3.7) ; extra == 'dev'
